LICENSE
README.md
setup.py
pysmart365/MicroSoftware.py
pysmart365/__init__.py
pysmart365/modules.py
pysmart365.egg-info/PKG-INFO
pysmart365.egg-info/SOURCES.txt
pysmart365.egg-info/dependency_links.txt
pysmart365.egg-info/requires.txt
pysmart365.egg-info/top_level.txt