Metadata-Version: 2.1
Name: pysmart365
Version: 0.1.0
Summary: This module is to simplify the functions of MicroSoftware and SmartSoft.
Home-page: https://github.com/informatic365/PySmart365/
Download-URL: https://pypi.org/project/pysmart365/
Author: Runkang
Author-email: informatic3650@gmail.com
License-File: LICENSE
